dataset.py
evaluation.py
models.py
stress_testing-0.1.data/scripts/test.py
stress_testing-0.1.data/scripts/train.py
stress_testing-0.1.dist-info/LICENSE
stress_testing-0.1.dist-info/METADATA
stress_testing-0.1.dist-info/WHEEL
stress_testing-0.1.dist-info/top_level.txt
stress_testing-0.1.dist-info/RECORD
