Metadata-Version: 2.1
Name: stress-testing
Version: 0.1
Summary: A Stress Testing Experiment on Different Sequential Models
Author: Ipek Erdogan
Author-email: ipek.erdogan@boun.edu.tr
Classifier: Programming Language :: Python :: 3
Classifier: License :: OSI Approved :: MIT License
Classifier: Operating System :: OS Independent
Requires-Python: >=3.8
License-File: LICENSE
Requires-Dist: numpy
Requires-Dist: torch
